{
  "$schema": "https://schema.management.azure.com/schemas/2019-04-01/deploymentTemplate.json#",
  "contentVersion": "1.0.0.0",
  "parameters": {
    "workspace": {
      "type": "String"
    }
  },
  "resources": [
    {
      "id": "[concat(resourceId('Microsoft.OperationalInsights/workspaces/providers', parameters('workspace'), 'Microsoft.SecurityInsights'), '/alertRules/707494a5-8e44-486b-90f8-155d1797a8eb')]",
      "name": "[concat(parameters('workspace'), '/Microsoft.SecurityInsights/707494a5-8e44-486b-90f8-155d1797a8eb')]",
      "type": "Microsoft.OperationalInsights/workspaces/providers/alertRules",
      "kind": "Scheduled",
      "apiVersion": "2023-12-01-preview",
      "properties": {
        "displayName": "Credential added after admin consented to Application",
        "description": "This query identifies instances where Service Principal credentials were added to an application after admin consent was granted.",
        "severity": "Medium",
        "enabled": true,

        "query": "let auditLookbackStart = 2d;\nlet auditLookbackEnd = 1d;\nAuditLogs\n| where TimeGenerated >= ago(auditLookbackStart)\n| where OperationName =~ \"Consent to application\"\n| where Result =~ \"success\"\n// Full query continues here",

        "queryFrequency": "P1D",
        "queryPeriod": "P2D",

        "triggerOperator": "GreaterThan",
        "triggerThreshold": 0,

        "suppressionDuration": "PT5H",
        "suppressionEnabled": false,

        "tactics": [
          "CredentialAccess",
          "Persistence",
          "PrivilegeEscalation"
        ],

        "techniques": [
          "T1555",
          "T1098"
        ],

        "incidentConfiguration": {
          "createIncident": true,
          "groupingConfiguration": {
            "enabled": true,
            "reopenClosedIncident": false,
            "lookbackDuration": "PT5H",
            "matchingMethod": "AllEntities",
            "groupByEntities": [],
            "groupByAlertDetails": [],
            "groupByCustomDetails": []
          }
        },

        "eventGroupingSettings": {
          "aggregationKind": "SingleAlert"
        },

        "entityMappings": [
          {
            "entityType": "Account",
            "fieldMappings": [
              {
                "identifier": "Name",
                "columnName": "Consent_InitiatingAppName"
              },
              {
                "identifier": "AadUserId",
                "columnName": "Consent_InitiatingAppServicePrincipalId"
              }
            ]
          },
          {
            "entityType": "IP",
            "fieldMappings": [
              {
                "identifier": "Address",
                "columnName": "Consent_InitiatingIpAddress"
              }
            ]
          }
        ],

        "customDetails": {},
        "alertDetailsOverride": null
      }
    }
  ]
}
